ds_store/__init__.py
ds_store/__main__.py
ds_store/buddy.py
ds_store/store.py
ds_store-1.3.2.dist-info/licenses/LICENSE
ds_store-1.3.2.dist-info/METADATA
ds_store-1.3.2.dist-info/WHEEL
ds_store-1.3.2.dist-info/entry_points.txt
ds_store-1.3.2.dist-info/top_level.txt
ds_store-1.3.2.dist-info/RECORD
