Metadata-Version: 2.4
Name: ds_store
Version: 1.3.2
Summary: Manipulate Finder .DS_Store files from Python
Author-email: Alastair Houghton <alastair@alastairs-place.net>
Maintainer-email: Russell Keith-Magee <russell@keith-magee.com>
License-Expression: MIT
Project-URL: Documentation, https://ds-store.readthedocs.io/en/latest/
Project-URL: Homepage, https://github.com/dmgbuild/ds_store
Project-URL: Tracker, https://github.com/dmgbuild/ds_store/issues
Project-URL: Source, https://github.com/dmgbuild/ds_store
Keywords: DS_Store
Classifier: Development Status :: 5 - Production/Stable
Classifier: Programming Language :: Python :: 3
Classifier: Programming Language :: Python :: 3.10
Classifier: Programming Language :: Python :: 3.11
Classifier: Programming Language :: Python :: 3.12
Classifier: Programming Language :: Python :: 3.13
Classifier: Programming Language :: Python :: 3.14
Classifier: Programming Language :: Python :: 3.15
Classifier: Programming Language :: Python :: 3 :: Only
Classifier: Topic :: Desktop Environment
Classifier: Topic :: Software Development :: Libraries :: Python Modules
Requires-Python: >=3.10
License-File: LICENSE
Requires-Dist: mac_alias>=2.2.2
Dynamic: license-file
